qsimpy/__init__.py
qsimpy/circuit.py
qsimpy/gates.py
qsimpy/simulator.py
qsimpy/utils.py
qsimpy-0.1.dist-info/LICENSE
qsimpy-0.1.dist-info/METADATA
qsimpy-0.1.dist-info/WHEEL
qsimpy-0.1.dist-info/top_level.txt
qsimpy-0.1.dist-info/RECORD
