Metadata-Version: 2.1
Name: qsimpy
Version: 0.1
Summary: A quantum simulator package
Home-page: https://github.com/SuhasPK/qsimpy
Author: Suhas P K
Author-email: sparrowjack0682@gmail.com
License: UNKNOWN
Platform: UNKNOWN
Classifier: Programming Language :: Python :: 3
Classifier: License :: OSI Approved :: MIT License
Classifier: Operating System :: OS Independent
Requires-Python: >=3.6
License-File: LICENSE
Requires-Dist: numpy>=1.21
